fmcardgen/__init__.py
fmcardgen/cli.py
fmcardgen/config.py
fmcardgen/draw.py
fmcardgen/frontmatter.py
fmcardgen/py.typed
fmcardgen-1.0.dist-info/METADATA
fmcardgen-1.0.dist-info/WHEEL
fmcardgen-1.0.dist-info/entry_points.txt
fmcardgen-1.0.dist-info/RECORD
