Metadata-Version: 2.4
Name: fmcardgen
Version: 1.0
Summary: generate images from documents with frontmatter
Author-email: Jacob Kaplan-Moss <jacob@jacobian.org>
Requires-Python: >=3.9
Requires-Dist: pillow>=11.2.1
Requires-Dist: pydantic-extra-types>=2.10.5
Requires-Dist: pydantic>=2.11.5
Requires-Dist: pygments>=2.19.1
Requires-Dist: python-dateutil>=2.9.0.post0
Requires-Dist: python-frontmatter>=1.1.0
Requires-Dist: pyyaml>=6.0.2
Requires-Dist: rich>=14.0.0
Requires-Dist: toml>=0.10.2
Requires-Dist: typer>=0.16.0
